wifitest/__init__.py
wifitest/__main__.py
wifitest/bruteforce.py
wifitest/cli.py
wifitest/events.py
wifitest/scan.py
wifitest/version.py
wifitest-0.1.9.dist-info/LICENSE
wifitest-0.1.9.dist-info/METADATA
wifitest-0.1.9.dist-info/WHEEL
wifitest-0.1.9.dist-info/entry_points.txt
wifitest-0.1.9.dist-info/top_level.txt
wifitest-0.1.9.dist-info/RECORD
